mathician/__init__.py
mathician-1.7.1.dist-info/LICENSE
mathician-1.7.1.dist-info/METADATA
mathician-1.7.1.dist-info/WHEEL
mathician-1.7.1.dist-info/top_level.txt
mathician-1.7.1.dist-info/RECORD
