Metadata-Version: 2.1
Name: mathician
Version: 1.7.1
Summary: Mathician is a math package that uses the math library (some of it) and built with Python math classes.
Author-email: Arjun Sharda <sharda.aj17@gmail.com>
License: MIT License
Project-URL: Homepage, https://github.com/ArjunSharda/Mathician
Project-URL: Bug Tracker, https://github.com/ArjunSharda/Mathician/issues
Classifier: Programming Language :: Python :: 3
Classifier: License :: OSI Approved :: MIT License
Classifier: Operating System :: OS Independent
Requires-Python: >=3.7
License-File: LICENSE
